{"match_id": "2866717", "home_team": "RCFC", "away_team": "Citizen", "final_score": null, "match_date": "2025-11-02", "match_time": "15:30", "match_datetime": "2025-11-02 15:30", "recent_indirect_full": {"last_home": {"home": "RCFC", "away": "Yuen Long FC", "score": "0 : 0", "ah": "1.25", "ou": "-", "stats_rows": [{"label": "Tiros", "home": "<span style=\"color: green; font-weight: bold;\">11</span>", "away": "<span style=\"color: red;\">4</span>"}, {"label": "Tiros a Puerta", "home": "3", "away": "3"}, {"label": "Ataques", "home": "<span style=\"color: green; font-weight: bold;\">64</span>", "away": "<span style=\"color: red;\">37</span>"}, {"label": "Ataques Peligrosos", "home": "<span style=\"color: green; font-weight: bold;\">54</span>", "away": "<span style=\"color: red;\">28</span>"}, {"label": "Red Cards", "home": "", "away": ""}], "date": "12-10-2025", "cover_status": "NO CUBIERTO"}, "last_away": {"home": "Kwun Tong", "away": "Citizen", "score": "1 : 1", "ah": "-0.75", "ou": "-", "stats_rows": [{"label": "Tiros", "home": "7", "away": "7"}, {"label": "Tiros a Puerta", "home": "<span style=\"color: red;\">2</span>", "away": "<span style=\"color: green; font-weight: bold;\">4</span>"}, {"label": "Ataques", "home": "<span style=\"color: red;\">44</span>", "away": "<span style=\"color: green; font-weight: bold;\">51</span>"}, {"label": "Ataques Peligrosos", "home": "<span style=\"color: red;\">41</span>", "away": "<span style=\"color: green; font-weight: bold;\">60</span>"}, {"label": "Red Cards", "home": "", "away": ""}], "date": "19-10-2025", "cover_status": "indeterminado"}, "h2h_col3": null, "h2h_general": {"home": "Citizen", "away": "RCFC", "score": "1 : 2", "ah": "1.5", "ou": "-", "stats_rows": [{"label": "Tiros", "home": "<span style=\"color: green; font-weight: bold;\">11</span>", "away": "<span style=\"color: red;\">8</span>"}, {"label": "Tiros a Puerta", "home": "<span style=\"color: red;\">4</span>", "away": "<span style=\"color: green; font-weight: bold;\">5</span>"}, {"label": "Ataques", "home": "<span style=\"color: green; font-weight: bold;\">118</span>", "away": "<span style=\"color: red;\">84</span>"}, {"label": "Ataques Peligrosos", "home": "<span style=\"color: green; font-weight: bold;\">84</span>", "away": "<span style=\"color: red;\">46</span>"}, {"label": "Red Cards", "home": "", "away": ""}], "date": null, "cover_status": "NO CUBIERTO"}}, "comparativas_indirectas": {"left": null, "right": {"title_home_name": "RCFC", "title_away_name": "Citizen", "home_team": "Citizen", "away_team": "Yuen Long FC", "score": "5 : 0", "ah": "1.5", "ou": "-", "localia": "H", "stats_rows": [{"label": "Tiros", "home": "<span style=\"color: green; font-weight: bold;\">18</span>", "away": "<span style=\"color: red;\">7</span>"}, {"label": "Tiros a Puerta", "home": "<span style=\"color: green; font-weight: bold;\">9</span>", "away": "<span style=\"color: red;\">2</span>"}, {"label": "Ataques", "home": "<span style=\"color: green; font-weight: bold;\">70</span>", "away": "<span style=\"color: red;\">66</span>"}, {"label": "Ataques Peligrosos", "home": "<span style=\"color: green; font-weight: bold;\">56</span>", "away": "<span style=\"color: red;\">35</span>"}, {"label": "Red Cards", "home": "<span style=\"color: red;\">0</span>", "away": "<span style=\"color: green; font-weight: bold;\">1</span>"}], "cover_status": "indeterminado", "analysis": "Contra este rival, el resultado para Citizen sería indeterminado"}}, "simplified_html": "<div class=\"card\"><div class=\"card-body\"><h6 class=\"card-title\">📊 Análisis Mercado vs. H2H</h6>\n            <div class=\"mb-2\">\n                <strong>Precedente (este estadio):</strong>\n                <div>Resultado: <span class=\"score-value\">0:3</span></div>\n                <div>Mov. Línea: <span class=\"ah-value\">-0.25 -> 1.75</span></div>\n                <div>Cobertura AH: <span style='color: red; font-weight: bold;'>NO CUBIERTO</span></div>\n            </div>\n        <hr>\n                <div class=\"mt-2\">\n                    <strong>Precedente (H2H mǭs reciente):</strong>\n                    <div>Resultado: <span class=\"score-value\">1:2</span></div>\n                    <div>Mov. Lnea: <span class=\"ah-value\">1.5 -> 1.75</span></div>\n                    <div>Cobertura AH: <span style='color: red; font-weight: bold;'>NO CUBIERTO</span></div>\n                </div>\n            </div></div>"}