{"match_id": "2872571", "home_team": "Al Jazira FC", "away_team": "Al-Sahel", "final_score": null, "match_date": "2025-10-20", "match_time": "22:40", "match_datetime": "2025-10-20 22:40", "recent_indirect_full": {"last_home": {"home": "Al Jazira FC", "away": "Sporty", "score": "3 : 0", "ah": "0.25", "ou": "-", "stats_rows": [{"label": "Tiros", "home": "<span style=\"color: green; font-weight: bold;\">17</span>", "away": "<span style=\"color: red;\">12</span>"}, {"label": "Tiros a Puerta", "home": "<span style=\"color: green; font-weight: bold;\">7</span>", "away": "<span style=\"color: red;\">1</span>"}, {"label": "Ataques", "home": "<span style=\"color: green; font-weight: bold;\">63</span>", "away": "<span style=\"color: red;\">60</span>"}, {"label": "Ataques Peligrosos", "home": "<span style=\"color: green; font-weight: bold;\">63</span>", "away": "<span style=\"color: red;\">40</span>"}, {"label": "Red Cards", "home": "", "away": ""}], "date": "22-09-2025", "cover_status": "CUBIERTO"}, "last_away": {"home": "Sporty", "away": "Al-Sahel", "score": "0 : 2", "ah": "-0.75", "ou": "-", "stats_rows": [{"label": "Tiros", "home": "<span style=\"color: red;\">5</span>", "away": "<span style=\"color: green; font-weight: bold;\">12</span>"}, {"label": "Tiros a Puerta", "home": "<span style=\"color: red;\">2</span>", "away": "<span style=\"color: green; font-weight: bold;\">4</span>"}, {"label": "Ataques", "home": "<span style=\"color: red;\">77</span>", "away": "<span style=\"color: green; font-weight: bold;\">89</span>"}, {"label": "Ataques Peligrosos", "home": "<span style=\"color: red;\">41</span>", "away": "<span style=\"color: green; font-weight: bold;\">52</span>"}, {"label": "Red Cards", "home": "", "away": ""}], "date": "29-09-2025", "cover_status": "indeterminado"}, "h2h_col3": null, "h2h_general": {"home": "Local (H2H Gen)", "away": "Visitante (H2H Gen)", "score": "? : ?", "ah": "-", "ou": "-", "stats_rows": [], "date": null, "cover_status": "NEUTRO"}}, "comparativas_indirectas": {"left": {"title_home_name": "Al Jazira FC", "title_away_name": "Al-Sahel", "home_team": "Al Jazira FC", "away_team": "Sporty", "score": "3 : 0", "ah": "0.25", "ou": "-", "localia": "H", "stats_rows": [{"label": "Tiros", "home": "<span style=\"color: green; font-weight: bold;\">17</span>", "away": "<span style=\"color: red;\">12</span>"}, {"label": "Tiros a Puerta", "home": "<span style=\"color: green; font-weight: bold;\">7</span>", "away": "<span style=\"color: red;\">1</span>"}, {"label": "Ataques", "home": "<span style=\"color: green; font-weight: bold;\">63</span>", "away": "<span style=\"color: red;\">60</span>"}, {"label": "Ataques Peligrosos", "home": "<span style=\"color: green; font-weight: bold;\">63</span>", "away": "<span style=\"color: red;\">40</span>"}, {"label": "Red Cards", "home": "", "away": ""}], "cover_status": "CUBIERTO", "analysis": "Contra este rival, Al Jazira FC habría cubierto el handicap"}, "right": {"title_home_name": "Al Jazira FC", "title_away_name": "Al-Sahel", "home_team": "Sporty", "away_team": "Al-Sahel", "score": "0 : 2", "ah": "-0.75", "ou": "-", "localia": "A", "stats_rows": [{"label": "Tiros", "home": "<span style=\"color: red;\">5</span>", "away": "<span style=\"color: green; font-weight: bold;\">12</span>"}, {"label": "Tiros a Puerta", "home": "<span style=\"color: red;\">2</span>", "away": "<span style=\"color: green; font-weight: bold;\">4</span>"}, {"label": "Ataques", "home": "<span style=\"color: red;\">77</span>", "away": "<span style=\"color: green; font-weight: bold;\">89</span>"}, {"label": "Ataques Peligrosos", "home": "<span style=\"color: red;\">41</span>", "away": "<span style=\"color: green; font-weight: bold;\">52</span>"}, {"label": "Red Cards", "home": "", "away": ""}], "cover_status": "indeterminado", "analysis": "Contra este rival, el resultado para Al-Sahel sería indeterminado"}}, "simplified_html": "<div class=\"card\"><div class=\"card-body\"><h6 class=\"card-title\">📊 Análisis Mercado vs. H2H</h6><p>No hay precedente H2H en este estadio.</p></div></div>"}