{"match_id": "2890398", "home_team": "Union Santa Fe Reserves", "away_team": "Barracas Central Reserves", "final_score": null, "match_date": "2025-10-24", "match_time": "02:00", "match_datetime": "2025-10-24 02:00", "recent_indirect_full": {"last_home": {"home": "Union Santa Fe Reserves", "away": "Defensa y Justicia Reserves", "score": "1 : 1", "ah": "0.5", "ou": "-", "stats_rows": [{"label": "Tiros", "home": "<span style=\"color: green; font-weight: bold;\">12</span>", "away": "<span style=\"color: red;\">6</span>"}, {"label": "Tiros a Puerta", "home": "<span style=\"color: green; font-weight: bold;\">3</span>", "away": "<span style=\"color: red;\">1</span>"}, {"label": "Ataques", "home": "<span style=\"color: green; font-weight: bold;\">131</span>", "away": "<span style=\"color: red;\">94</span>"}, {"label": "Ataques Peligrosos", "home": "<span style=\"color: green; font-weight: bold;\">90</span>", "away": "<span style=\"color: red;\">38</span>"}, {"label": "Red Cards", "home": "", "away": ""}], "date": "07-10-2025", "cover_status": "NO CUBIERTO"}, "last_away": {"home": "Tigre Reserves", "away": "Barracas Central Reserves", "score": "0 : 1", "ah": "0.25", "ou": "-", "stats_rows": [{"label": "Tiros", "home": "<span style=\"color: red;\">10</span>", "away": "<span style=\"color: green; font-weight: bold;\">15</span>"}, {"label": "Tiros a Puerta", "home": "<span style=\"color: red;\">5</span>", "away": "<span style=\"color: green; font-weight: bold;\">6</span>"}, {"label": "Ataques", "home": "<span style=\"color: green; font-weight: bold;\">104</span>", "away": "<span style=\"color: red;\">92</span>"}, {"label": "Ataques Peligrosos", "home": "<span style=\"color: green; font-weight: bold;\">61</span>", "away": "<span style=\"color: red;\">49</span>"}, {"label": "Red Cards", "home": "", "away": ""}], "date": "08-10-2025", "cover_status": "indeterminado"}, "h2h_col3": {"home": "Tigre Reserves", "away": "Defensa y Justicia Reserves", "score": "2 : 1", "ah": "-", "ou": "-", "stats_rows": [{"label": "Tiros", "home": "<span style=\"color: green; font-weight: bold;\">12</span>", "away": "<span style=\"color: red;\">11</span>"}, {"label": "Tiros a Puerta", "home": "<span style=\"color: green; font-weight: bold;\">4</span>", "away": "<span style=\"color: red;\">2</span>"}, {"label": "Ataques", "home": "<span style=\"color: green; font-weight: bold;\">103</span>", "away": "<span style=\"color: red;\">91</span>"}, {"label": "Ataques Peligrosos", "home": "<span style=\"color: green; font-weight: bold;\">53</span>", "away": "<span style=\"color: red;\">47</span>"}, {"label": "Red Cards", "home": "<span style=\"color: red;\">0</span>", "away": "<span style=\"color: green; font-weight: bold;\">1</span>"}], "date": "", "cover_status": "indeterminado", "analysis": null}, "h2h_general": {"home": "Barracas Central Reserves", "away": "Union Santa Fe Reserves", "score": "0 : 1", "ah": "0", "ou": "-", "stats_rows": [{"label": "Tiros", "home": "<span style=\"color: red;\">7</span>", "away": "<span style=\"color: green; font-weight: bold;\">11</span>"}, {"label": "Tiros a Puerta", "home": "<span style=\"color: red;\">3</span>", "away": "<span style=\"color: green; font-weight: bold;\">5</span>"}, {"label": "Ataques", "home": "<span style=\"color: red;\">114</span>", "away": "<span style=\"color: green; font-weight: bold;\">131</span>"}, {"label": "Ataques Peligrosos", "home": "<span style=\"color: red;\">59</span>", "away": "<span style=\"color: green; font-weight: bold;\">74</span>"}, {"label": "Red Cards", "home": "", "away": ""}], "date": null, "cover_status": "CUBIERTO"}}, "comparativas_indirectas": {"left": {"title_home_name": "Union Santa Fe Reserves", "title_away_name": "Barracas Central Reserves", "home_team": "Union Santa Fe Reserves", "away_team": "Tigre Reserves", "score": "3 : 2", "ah": "0.25", "ou": "-", "localia": "H", "stats_rows": [{"label": "Tiros", "home": "<span style=\"color: green; font-weight: bold;\">14</span>", "away": "<span style=\"color: red;\">7</span>"}, {"label": "Tiros a Puerta", "home": "<span style=\"color: green; font-weight: bold;\">9</span>", "away": "<span style=\"color: red;\">2</span>"}, {"label": "Ataques", "home": "<span style=\"color: green; font-weight: bold;\">94</span>", "away": "<span style=\"color: red;\">77</span>"}, {"label": "Ataques Peligrosos", "home": "<span style=\"color: red;\">59</span>", "away": "<span style=\"color: green; font-weight: bold;\">64</span>"}, {"label": "Red Cards", "home": "", "away": ""}], "cover_status": "CUBIERTO", "analysis": "Contra este rival, Union Santa Fe Reserves habría cubierto el handicap"}, "right": {"title_home_name": "Union Santa Fe Reserves", "title_away_name": "Barracas Central Reserves", "home_team": "Barracas Central Reserves", "away_team": "Defensa y Justicia Reserves", "score": "2 : 1", "ah": "0", "ou": "-", "localia": "H", "stats_rows": [{"label": "Tiros", "home": "<span style=\"color: red;\">6</span>", "away": "<span style=\"color: green; font-weight: bold;\">8</span>"}, {"label": "Tiros a Puerta", "home": "3", "away": "3"}, {"label": "Ataques", "home": "<span style=\"color: red;\">100</span>", "away": "<span style=\"color: green; font-weight: bold;\">111</span>"}, {"label": "Ataques Peligrosos", "home": "<span style=\"color: red;\">62</span>", "away": "<span style=\"color: green; font-weight: bold;\">99</span>"}, {"label": "Red Cards", "home": "", "away": ""}], "cover_status": "indeterminado", "analysis": "Contra este rival, el resultado para Barracas Central Reserves sería indeterminado"}}, "simplified_html": "<div class=\"card\"><div class=\"card-body\"><h6 class=\"card-title\">📊 Análisis Mercado vs. H2H</h6>\n            <div class=\"mb-2\">\n                <strong>Precedente (este estadio):</strong>\n                <div>Resultado: <span class=\"score-value\">2:0</span></div>\n                <div>Mov. Línea: <span class=\"ah-value\">1 -> 0.5</span></div>\n                <div>Cobertura AH: <span style='color: green; font-weight: bold;'>CUBIERTO</span></div>\n            </div>\n        <hr>\n                <div class=\"mt-2\">\n                    <strong>Precedente (H2H mǭs reciente):</strong>\n                    <div>Resultado: <span class=\"score-value\">0:1</span></div>\n                    <div>Mov. Lnea: <span class=\"ah-value\">0 -> 0.5</span></div>\n                    <div>Cobertura AH: <span style='color: green; font-weight: bold;'>CUBIERTO</span></div>\n                </div>\n            </div></div>"}