{"match_id": "2896102", "home_team": "Apollon Limassol LFC (W)", "away_team": "Lakatamia FC (W)", "final_score": null, "match_date": "2025-11-02", "match_time": "16:00", "match_datetime": "2025-11-02 16:00", "recent_indirect_full": {"last_home": {"home": "Apollon Limassol LFC (W)", "away": "Lakatamia FC (W)", "score": "4 : 0", "ah": "2.75", "ou": "-", "stats_rows": [{"label": "Tiros", "home": "<span style=\"color: green; font-weight: bold;\">17</span>", "away": "<span style=\"color: red;\">4</span>"}, {"label": "Tiros a Puerta", "home": "<span style=\"color: green; font-weight: bold;\">10</span>", "away": "<span style=\"color: red;\">1</span>"}, {"label": "Ataques", "home": "<span style=\"color: green; font-weight: bold;\">105</span>", "away": "<span style=\"color: red;\">63</span>"}, {"label": "Ataques Peligrosos", "home": "<span style=\"color: green; font-weight: bold;\">55</span>", "away": "<span style=\"color: red;\">26</span>"}, {"label": "Red Cards", "home": "", "away": ""}], "date": "16-03-2025", "cover_status": "CUBIERTO"}, "last_away": {"home": "Olympiakos Nicosia FC（W）", "away": "Lakatamia FC (W)", "score": "1 : 2", "ah": "-", "ou": "-", "stats_rows": [{"label": "Tiros", "home": "<span style=\"color: red;\">9</span>", "away": "<span style=\"color: green; font-weight: bold;\">13</span>"}, {"label": "Tiros a Puerta", "home": "<span style=\"color: red;\">4</span>", "away": "<span style=\"color: green; font-weight: bold;\">8</span>"}, {"label": "Ataques", "home": "<span style=\"color: red;\">94</span>", "away": "<span style=\"color: green; font-weight: bold;\">143</span>"}, {"label": "Ataques Peligrosos", "home": "<span style=\"color: red;\">96</span>", "away": "<span style=\"color: green; font-weight: bold;\">108</span>"}, {"label": "Red Cards", "home": "", "away": ""}], "date": "12-10-2025", "cover_status": "indeterminado"}, "h2h_col3": null, "h2h_general": {"home": "Apollon Limassol LFC (W)", "away": "Lakatamia FC (W)", "score": "4 : 1", "ah": "3.25", "ou": "-", "stats_rows": [{"label": "Tiros", "home": "<span style=\"color: green; font-weight: bold;\">17</span>", "away": "<span style=\"color: red;\">4</span>"}, {"label": "Tiros a Puerta", "home": "<span style=\"color: green; font-weight: bold;\">11</span>", "away": "<span style=\"color: red;\">2</span>"}, {"label": "Ataques", "home": "<span style=\"color: green; font-weight: bold;\">128</span>", "away": "<span style=\"color: red;\">77</span>"}, {"label": "Ataques Peligrosos", "home": "<span style=\"color: green; font-weight: bold;\">89</span>", "away": "<span style=\"color: red;\">28</span>"}, {"label": "Red Cards", "home": "", "away": ""}], "date": null, "cover_status": "NO CUBIERTO"}}, "comparativas_indirectas": {"left": null, "right": null}, "simplified_html": "<div class=\"card\"><div class=\"card-body\"><h6 class=\"card-title\">📊 Análisis Mercado vs. H2H</h6>\n            <div class=\"mb-2\">\n                <strong>Precedente (este estadio):</strong>\n                <div>Resultado: <span class=\"score-value\">4:1</span></div>\n                <div>Mov. Línea: <span class=\"ah-value\">3.25 -> 3.5</span></div>\n                <div>Cobertura AH: <span style='color: red; font-weight: bold;'>NO CUBIERTO</span></div>\n            </div>\n        \n                <div class=\"mt-2\">\n                    <strong>Precedente (H2H mǭs reciente):</strong>\n                    <div>Resultado: <span class=\"score-value\">4:1</span></div>\n                    <div>Mov. Lnea: <span class=\"ah-value\">3.25 -> 3.5</span></div>\n                    <div>Cobertura AH: <span style='color: red; font-weight: bold;'>NO CUBIERTO</span></div>\n                </div>\n            </div></div>"}